surrealdb_beta-0.0.5.dist-info/RECORD
surrealdb_beta-0.0.5.dist-info/METADATA
surrealdb_beta-0.0.5.dist-info/WHEEL
surrealdb_beta-0.0.5.dist-info/top_level.txt
surrealdb_beta-0.0.5.dist-info/LICENSE
surrealdb/connection_interface.py
surrealdb/__init__.py
surrealdb/errors.py
surrealdb/rust_surrealdb.pypy39-pp73-x86-linux-gnu.so
surrealdb/async_connection_interface.py
surrealdb/VERSION.txt
surrealdb/asyncio_runtime.py
surrealdb/http.py
surrealdb/execution_mixins/__init__.py
surrealdb/execution_mixins/query.py
surrealdb/execution_mixins/auth.py
surrealdb/execution_mixins/set.py
surrealdb/execution_mixins/update.py
surrealdb/execution_mixins/create.py
surrealdb/async_execution_mixins/__init__.py
surrealdb/async_execution_mixins/query.py
surrealdb/async_execution_mixins/auth.py
surrealdb/async_execution_mixins/set.py
surrealdb/async_execution_mixins/update.py
surrealdb/async_execution_mixins/create.py
