Metadata-Version: 2.1
Name: surrealdb-beta
Version: 0.0.5
Summary: SurrealDB python client written in Rust.
Author: Maxwell Flitton
Author-email: maxwell@gmail.com
License-File: LICENSE
